CHANGES.txt
CONTRIBUTORS.txt
README.txt
bootstrap.py
buildout.cfg
setup.cfg
setup.py
iw/__init__.py
iw.recipe.backup.egg-info/PKG-INFO
iw.recipe.backup.egg-info/SOURCES.txt
iw.recipe.backup.egg-info/dependency_links.txt
iw.recipe.backup.egg-info/entry_points.txt
iw.recipe.backup.egg-info/namespace_packages.txt
iw.recipe.backup.egg-info/not-zip-safe
iw.recipe.backup.egg-info/requires.txt
iw.recipe.backup.egg-info/top_level.txt
iw/recipe/__init__.py
iw/recipe/backup/README.txt
iw/recipe/backup/__init__.py
iw/recipe/backup/archive.py
iw/recipe/backup/filestorage.py
iw/recipe/backup/testing.py
iw/recipe/backup/tests/Data.fs
iw/recipe/backup/tests/__init__.py
iw/recipe/backup/tests/test_docs.py