Metadata-Version: 1.0
Name: iw.recipe.backup
Version: 0.2.1
Summary: Zc buildout recipe that provides a backup script
Home-page: https://ingeniweb.svn.sourceforge.net/svnroot/ingeniweb/iw.recipe.backup
Author: Ingeniweb
Author-email: support@ingeniweb.com
License: ZPL
Keywords: recipe buildout
Platform: UNKNOWN
Classifier: Framework :: Buildout
Classifier: Intended Audience :: Developers
Classifier: Topic :: Software Development :: Build Tools
Classifier: Topic :: Software Development :: Libraries :: Python Modules
Classifier: License :: OSI Approved :: Zope Public License
